{
  "ATLAS": {
    "SPRITES": [
      {
        "SPRITE": {
          "name": "0",
          "x": 2,
          "y": 389,
          "w": 302,
          "h": 369,
          "rotated": false
        }
      },
      {
        "SPRITE": {
          "name": "1",
          "x": 590,
          "y": 389,
          "w": 117,
          "h": 185,
          "rotated": true
        }
      },
      {
        "SPRITE": {
          "name": "2",
          "x": 837,
          "y": 493,
          "w": 136,
          "h": 86,
          "rotated": true
        }
      },
      {
        "SPRITE": {
          "name": "3",
          "x": 885,
          "y": 2,
          "w": 100,
          "h": 243,
          "rotated": true
        }
      },
      {
        "SPRITE": {
          "name": "4",
          "x": 677,
          "y": 587,
          "w": 122,
          "h": 68,
          "rotated": false
        }
      },
      {
        "SPRITE": {
          "name": "5",
          "x": 708,
          "y": 389,
          "w": 128,
          "h": 110,
          "rotated": true
        }
      },
      {
        "SPRITE": {
          "name": "6",
          "x": 885,
          "y": 246,
          "w": 105,
          "h": 148,
          "rotated": false
        }
      },
      {
        "SPRITE": {
          "name": "7",
          "x": 837,
          "y": 395,
          "w": 131,
          "h": 97,
          "rotated": true
        }
      },
      {
        "SPRITE": {
          "name": "8",
          "x": 2,
          "y": 2,
          "w": 882,
          "h": 386,
          "rotated": false
        }
      },
      {
        "SPRITE": {
          "name": "9",
          "x": 708,
          "y": 500,
          "w": 120,
          "h": 86,
          "rotated": false
        }
      },
      {
        "SPRITE": {
          "name": "10",
          "x": 590,
          "y": 575,
          "w": 86,
          "h": 120,
          "rotated": true
        }
      },
      {
        "SPRITE": {
          "name": "11",
          "x": 677,
          "y": 667,
          "w": 105,
          "h": 86,
          "rotated": false
        }
      },
      {
        "SPRITE": {
          "name": "12",
          "x": 829,
          "y": 580,
          "w": 120,
          "h": 86,
          "rotated": false
        }
      },
      {
        "SPRITE": {
          "name": "13",
          "x": 305,
          "y": 389,
          "w": 284,
          "h": 362,
          "rotated": false
        }
      }
    ]
  },
  "meta": {
    "app": "Adobe Animate (Better TA Extension)",
    "version": "23.0.15.4",
    "image": "spritemap1.png",
    "format": "RGBA8888",
    "size": { "w": 992, "h": 760 },
    "resolution": "1"
  }
}
